napari_hough_circle_detector/__init__.py
napari_hough_circle_detector/napari.yaml
napari_hough_circle_detector-0.0.5.dist-info/LICENSE
napari_hough_circle_detector-0.0.5.dist-info/METADATA
napari_hough_circle_detector-0.0.5.dist-info/WHEEL
napari_hough_circle_detector-0.0.5.dist-info/entry_points.txt
napari_hough_circle_detector-0.0.5.dist-info/top_level.txt
napari_hough_circle_detector-0.0.5.dist-info/RECORD
