Metadata-Version: 2.1
Name: napari-hough-circle-detector
Version: 0.0.5
Summary: An interactive Hough transform for napari.
Author: Florian Aymanns
Author-email: florian.aymanns@epfl.ch
Maintainer: Florian Aymanns
Maintainer-email: florian.aymanns@epfl.ch
Keywords: napari,hough
Classifier: Framework :: napari
License-File: LICENSE
Requires-Dist: napari[all]
Requires-Dist: opencv-contrib-python-headless
Requires-Dist: numpy
Requires-Dist: pyqt5
Requires-Dist: scikit-image
